odoo8_addon_base_transaction_id-8.0.1.0.0.99.dev29-py3.8-nspkg.pth
odoo_addons/base_transaction_id/__init__.py
odoo_addons/base_transaction_id/__openerp__.py
odoo_addons/base_transaction_id/account_bank_statement.py
odoo_addons/base_transaction_id/account_move.py
odoo_addons/base_transaction_id/account_move_line_view.xml
odoo_addons/base_transaction_id/invoice.py
odoo_addons/base_transaction_id/invoice_view.xml
odoo_addons/base_transaction_id/sale.py
odoo_addons/base_transaction_id/sale_view.xml
odoo_addons/base_transaction_id/stock.py
odoo_addons/base_transaction_id/i18n/ar.po
odoo_addons/base_transaction_id/i18n/base_transaction_id.pot
odoo_addons/base_transaction_id/i18n/bg.po
odoo_addons/base_transaction_id/i18n/bs.po
odoo_addons/base_transaction_id/i18n/ca.po
odoo_addons/base_transaction_id/i18n/cs.po
odoo_addons/base_transaction_id/i18n/de.po
odoo_addons/base_transaction_id/i18n/el_GR.po
odoo_addons/base_transaction_id/i18n/en_GB.po
odoo_addons/base_transaction_id/i18n/es.po
odoo_addons/base_transaction_id/i18n/es_AR.po
odoo_addons/base_transaction_id/i18n/es_CR.po
odoo_addons/base_transaction_id/i18n/es_EC.po
odoo_addons/base_transaction_id/i18n/es_ES.po
odoo_addons/base_transaction_id/i18n/es_MX.po
odoo_addons/base_transaction_id/i18n/es_PE.po
odoo_addons/base_transaction_id/i18n/et.po
odoo_addons/base_transaction_id/i18n/fi.po
odoo_addons/base_transaction_id/i18n/fr.po
odoo_addons/base_transaction_id/i18n/fr_CA.po
odoo_addons/base_transaction_id/i18n/fr_CH.po
odoo_addons/base_transaction_id/i18n/gl.po
odoo_addons/base_transaction_id/i18n/hr.po
odoo_addons/base_transaction_id/i18n/hr_HR.po
odoo_addons/base_transaction_id/i18n/hu.po
odoo_addons/base_transaction_id/i18n/id.po
odoo_addons/base_transaction_id/i18n/it.po
odoo_addons/base_transaction_id/i18n/ja.po
odoo_addons/base_transaction_id/i18n/lt.po
odoo_addons/base_transaction_id/i18n/mk.po
odoo_addons/base_transaction_id/i18n/mn.po
odoo_addons/base_transaction_id/i18n/nb.po
odoo8_addon_base_transaction_id-8.0.1.0.0.99.dev29.dist-info/METADATA
odoo8_addon_base_transaction_id-8.0.1.0.0.99.dev29.dist-info/WHEEL
odoo8_addon_base_transaction_id-8.0.1.0.0.99.dev29.dist-info/namespace_packages.txt
odoo8_addon_base_transaction_id-8.0.1.0.0.99.dev29.dist-info/top_level.txt
odoo8_addon_base_transaction_id-8.0.1.0.0.99.dev29.dist-info/RECORD
